{
  "Name": "arc-lash-sorcerer.",
  "ItemAffixes": [
    {
      "Id": "CritDamage",
      "Type": "Weapon"
    },
    {
      "Id": "CritDamage_With_Lightning",
      "Type": "Weapon"
    },
    {
      "Id": "CoreStats_All",
      "Type": "Weapon"
    },
    {
      "Id": "Damage_to_Near",
      "Type": "Weapon"
    },
    {
      "Id": "CoreStat_Intelligence",
      "Type": "Weapon"
    },
    {
      "Id": "AttackSpeed_Basics",
      "Type": "Off-Hand"
    },
    {
      "Id": "CritChance",
      "Type": "Off-Hand"
    },
    {
      "Id": "Luck",
      "Type": "Off-Hand"
    },
    {
      "Id": "CoreStat_Intelligence",
      "Type": "Off-Hand"
    },
    {
      "Id": "CD_Reduction",
      "Type": "Off-Hand"
    },
    {
      "Id": "Life",
      "Type": "Helm"
    },
    {
      "Id": "AttackSpeed_Basics",
      "Type": "Helm"
    },
    {
      "Id": "Armor",
      "Type": "Helm"
    },
    {
      "Id": "Luck_With_Barrier",
      "Type": "Helm"
    },
    {
      "Id": "CoreStat_Intelligence",
      "Type": "Helm"
    },
    {
      "Id": "CD_Reduction",
      "Type": "Helm"
    },
    {
      "Id": "Life",
      "Type": "Chest"
    },
    {
      "Id": "Armor",
      "Type": "Chest"
    },
    {
      "Id": "DamageReductionClose",
      "Type": "Chest"
    },
    {
      "Id": "DamageReduction",
      "Type": "Chest"
    },
    {
      "Id": "CoreStat_Intelligence",
      "Type": "Chest"
    },
    {
      "Id": "DamageReductionDistant",
      "Type": "Chest"
    },
    {
      "Id": "CritDamage_With_Lightning",
      "Type": "Gloves"
    },
    {
      "Id": "Luck",
      "Type": "Gloves"
    },
    {
      "Id": "AttackSpeed",
      "Type": "Gloves"
    },
    {
      "Id": "CritChance",
      "Type": "Gloves"
    },
    {
      "Id": "Luck",
      "Type": "Gloves"
    },
    {
      "Id": "CoreStat_Intelligence",
      "Type": "Gloves"
    },
    {
      "Id": "Life",
      "Type": "Pants"
    },
    {
      "Id": "Armor",
      "Type": "Pants"
    },
    {
      "Id": "SkillRankBonus_Sorc_Special_BallLightning",
      "Type": "Pants"
    },
    {
      "Id": "DamageReductionClose",
      "Type": "Pants"
    },
    {
      "Id": "DamageReduction",
      "Type": "Pants"
    },
    {
      "Id": "CoreStat_Intelligence",
      "Type": "Pants"
    },
    {
      "Id": "DamageReductionDistant",
      "Type": "Pants"
    },
    {
      "Id": "SkillRankBonus_Sorc_Special_FlameShield",
      "Type": "Boots"
    },
    {
      "Id": "SkillRankBonus_Sorc_Special_Teleport",
      "Type": "Boots"
    },
    {
      "Id": "Movement_Speed",
      "Type": "Boots"
    },
    {
      "Id": "CoreStat_Intelligence",
      "Type": "Boots"
    },
    {
      "Id": "SkillRankBonus_Sorc_Special_FrostNova",
      "Type": "Boots"
    },
    {
      "Id": "PassiveRankBonus_Sorc_02_ConjurationMastery",
      "Type": "Amulet"
    },
    {
      "Id": "PassiveRankBonus_Sorc_01_Hoarfrost",
      "Type": "Amulet"
    },
    {
      "Id": "SkillRankBonus_Generic_Category_Defensive",
      "Type": "Amulet"
    },
    {
      "Id": "DamageReductionClose",
      "Type": "Amulet"
    },
    {
      "Id": "Movement_Speed",
      "Type": "Amulet"
    },
    {
      "Id": "CD_Reduction",
      "Type": "Amulet"
    },
    {
      "Id": "Life",
      "Type": "Ring"
    },
    {
      "Id": "CritDamage",
      "Type": "Ring"
    },
    {
      "Id": "CritDamage_With_Lightning",
      "Type": "Ring"
    },
    {
      "Id": "Damage_to_Near",
      "Type": "Ring"
    },
    {
      "Id": "CritChance",
      "Type": "Ring"
    },
    {
      "Id": "Luck",
      "Type": "Ring"
    }
  ],
  "ItemAspects": []
}