{
  "Name": "blood-surge-necromancer.",
  "ItemAffixes": [
    {
      "Id": "Damage_Category_Spenders",
      "Type": "Weapon"
    },
    {
      "Id": "CoreStats_All",
      "Type": "Weapon"
    },
    {
      "Id": "Damage_to_Near",
      "Type": "Weapon"
    },
    {
      "Id": "OverpowerDamage",
      "Type": "Weapon"
    },
    {
      "Id": "CoreStat_Intelligence",
      "Type": "Weapon"
    },
    {
      "Id": "Life",
      "Type": "Off-Hand\n(Shield)"
    },
    {
      "Id": "Lucky_Hit_Resource",
      "Type": "Off-Hand\n(Shield)"
    },
    {
      "Id": "Resource_Cost_Reduction_Necromancer",
      "Type": "Off-Hand\n(Shield)"
    },
    {
      "Id": "DamageReductionClose",
      "Type": "Off-Hand\n(Shield)"
    },
    {
      "Id": "Luck",
      "Type": "Off-Hand\n(Shield)"
    },
    {
      "Id": "CD_Reduction",
      "Type": "Off-Hand\n(Shield)"
    },
    {
      "Id": "Life",
      "Type": "Helm"
    },
    {
      "Id": "HealingPercent",
      "Type": "Helm"
    },
    {
      "Id": "Armor",
      "Type": "Helm"
    },
    {
      "Id": "CoreStats_All",
      "Type": "Helm"
    },
    {
      "Id": "CD_Reduction",
      "Type": "Helm"
    },
    {
      "Id": "Life",
      "Type": "Chest"
    },
    {
      "Id": "DamageReductionDistant",
      "Type": "Chest"
    },
    {
      "Id": "Armor",
      "Type": "Chest"
    },
    {
      "Id": "DamageReduction",
      "Type": "Chest"
    },
    {
      "Id": "DamageReductionClose",
      "Type": "Chest"
    },
    {
      "Id": "Lucky_Hit_Resource",
      "Type": "Gloves"
    },
    {
      "Id": "SkillRankBonus_Necro_Core_5",
      "Type": "Gloves"
    },
    {
      "Id": "AttackSpeed",
      "Type": "Gloves"
    },
    {
      "Id": "OverpowerDamage",
      "Type": "Gloves"
    },
    {
      "Id": "CritChance",
      "Type": "Gloves"
    },
    {
      "Id": "Luck",
      "Type": "Gloves"
    },
    {
      "Id": "Life",
      "Type": "Pants"
    },
    {
      "Id": "BloodOrb_Healing",
      "Type": "Pants"
    },
    {
      "Id": "FortifyDamageReduction",
      "Type": "Pants"
    },
    {
      "Id": "Armor",
      "Type": "Pants"
    },
    {
      "Id": "Movement_Speed",
      "Type": "Boots"
    },
    {
      "Id": "BloodOrb_Healing",
      "Type": "Boots"
    },
    {
      "Id": "SkillRankBonus_Necro_Special_CorpseTendrils",
      "Type": "Boots"
    },
    {
      "Id": "Resource_Cost_Reduction_Necromancer",
      "Type": "Boots"
    },
    {
      "Id": "Armor",
      "Type": "Amulet"
    },
    {
      "Id": "Resource_Cost_Reduction_Necromancer",
      "Type": "Amulet"
    },
    {
      "Id": "PassiveRankBonus_Necro_Playstyle_T1_N2_TidesofBlood",
      "Type": "Amulet"
    },
    {
      "Id": "Movement_Speed",
      "Type": "Amulet"
    },
    {
      "Id": "CD_Reduction",
      "Type": "Amulet"
    },
    {
      "Id": "PassiveRankBonus_Necro_Caster_T2_N2_CoalescedBlood",
      "Type": "Amulet"
    },
    {
      "Id": "Life",
      "Type": "Ring"
    },
    {
      "Id": "BloodOrb_Healing",
      "Type": "Ring"
    },
    {
      "Id": "OverpowerDamage",
      "Type": "Ring"
    },
    {
      "Id": "CritChance",
      "Type": "Ring"
    },
    {
      "Id": "Luck",
      "Type": "Ring"
    },
    {
      "Id": "Life",
      "Type": "Ring"
    },
    {
      "Id": "BloodOrb_Healing",
      "Type": "Ring"
    },
    {
      "Id": "OverpowerDamage",
      "Type": "Ring"
    },
    {
      "Id": "CritChance",
      "Type": "Ring"
    },
    {
      "Id": "Luck",
      "Type": "Ring"
    }
  ],
  "ItemAspects": []
}